{
  "dataset_name": "Number of dwelling units approved, by sector, all series - New South Wales",
  "source": "User Provided (Excel File)",
  "original_source": "Provided locally in dataset folder (moved to raw/ when processed)",
  "description": "Cleaned and ML-prepared dataset of dwelling units approved in New South Wales by sector and series.",
  "created_date": "2026-05-04",
  "data_cleaning": {
    "duplicates_removed": null,
    "missing_values_handled": "Median for numeric, Mode for categorical",
    "outliers_removed_method": "Not applied",
    "categorical_encoding": "Label encoding for small-cardinality columns"
  },
  "ml_preparation": {
    "numeric_scaled": null,
    "categorical_label_encoded": null,
    "scaler_file": "features/scaler.pkl",
    "encoders_file": "features/encoders.pkl"
  },
  "features_engineered": "Basic encoding and scaling applied",
  "total_samples": null,
  "total_features": null,
  "files": {
    "raw": "raw/<original_excel_name>.xlsx",
    "cleaned": "processed/nsw_dwelling_units_clean.csv",
    "features_scaled": "features/nsw_dwelling_units_features_scaled.csv",
    "scaler": "features/scaler.pkl",
    "encoders": "features/encoders.pkl",
    "metadata": "metadata.json"
  }
}